models/__init__.py
models/employee_transfer.py
models/hr_contract.py
odoo_addon_branch_transfer-17.0.1.0.0.dist-info/METADATA
odoo_addon_branch_transfer-17.0.1.0.0.dist-info/WHEEL
odoo_addon_branch_transfer-17.0.1.0.0.dist-info/entry_points.txt
odoo_addon_branch_transfer-17.0.1.0.0.dist-info/top_level.txt
odoo_addon_branch_transfer-17.0.1.0.0.dist-info/RECORD
