Metadata-Version: 2.1
Name: odoo-addon-branch-transfer
Version: 17.0.1.0.0
Summary: Employee transfer between branches in Odoo HR
Home-page: https://cybrosys.com
Author: Cybrosys Techno Solutions, Open HRMS
Author-email: info@cybrosys.com
License: LGPL-3
Classifier: Programming Language :: Python :: 3
Classifier: License :: OSI Approved :: GNU Lesser General Public License v3 (LGPLv3)
Classifier: Framework :: Odoo
Classifier: Operating System :: OS Independent
Requires-Python: >=3.8
